Metadata-Version: 2.1
Name: aioimap
Version: 0.2.5
Summary: Receive e-mails from an IMAP server asynchronously and trigger a callback with the message.
Home-page: https://github.com/surajiyer/aioimap
Author: Suraj Iyer
Author-email: me@surajiyer.com
License: MIT
Platform: UNKNOWN
